{
  "project_info": {
    "project_number": "632674665698",
    "project_id": "aboutme-project",
    "storage_bucket": "aboutme-project.appspot.com"
  },
  "client": [
    {
      "client_info": {
        "mobilesdk_app_id": "1:632674665698:android:4f95a4e3510aaa49350abb",
        "android_client_info": {
          "package_name": "com.example.aboutme"
        }
      },
      "oauth_client": [
        {
          "client_id": "632674665698-v1vtp4guk94ujsn62hufblt4e7fg035k.apps.googleusercontent.com",
          "client_type": 3
        }
      ],
      "api_key": [
        {
          "current_key": "AIzaSyCK4tSiSDcJhH63XQCf3NBmQrBszfoef6k"
        }
      ],
      "services": {
        "appinvite_service": {
          "other_platform_oauth_client": [
            {
              "client_id": "632674665698-v1vtp4guk94ujsn62hufblt4e7fg035k.apps.googleusercontent.com",
              "client_type": 3
            }
          ]
        }
      }
    }
  ],
  "configuration_version": "1"
}